{
  "best_score": 5.6768,
  "iteration": 66,
  "phase": 4,
  "phase_note": "Phase 4: Reality-check layer. Win rate penalty (>70% or <35%), PF capped at 4x, too-clean DD penalty (<1%), Sharpe capped at 3.0, min 20 trades. Target: score > 8.0.",
  "run_history": [
    {
      "iteration": 0,
      "score": -7.6411,
      "result": "baseline (Phase 3 strategy re-scored under Phase 4 rules)"
    },
    {
      "iteration": 1,
      "score": -1.0396,
      "result": "kept"
    },
    {
      "iteration": 2,
      "score": 0.1884,
      "result": "kept"
    },
    {
      "iteration": 5,
      "score": 1.3583,
      "result": "kept"
    },
    {
      "iteration": 6,
      "score": 2.3978,
      "result": "kept"
    },
    {
      "iteration": 12,
      "score": 3.4943,
      "result": "kept"
    },
    {
      "iteration": 20,
      "score": 4.958,
      "result": "kept"
    },
    {
      "iteration": 46,
      "score": 5.2164,
      "result": "kept"
    },
    {
      "iteration": 65,
      "score": 5.3139,
      "result": "kept"
    },
    {
      "iteration": 66,
      "score": 5.6768,
      "result": "kept"
    }
  ]
}